twistnsync/__init__.py
twistnsync/twistnsync.py
twistnsync-0.3.0.dist-info/LICENSE
twistnsync-0.3.0.dist-info/WHEEL
twistnsync-0.3.0.dist-info/METADATA
twistnsync-0.3.0.dist-info/RECORD
